lnxlink/__init__.py
lnxlink/__main__.py
lnxlink/config_setup.py
lnxlink/consts.py
lnxlink/files_setup.py
lnxlink/mqtt.py
lnxlink/system_monitor.py
lnxlink/modules/__init__.py
lnxlink/modules/active_window.py
lnxlink/modules/audio_select.py
lnxlink/modules/bash.py
lnxlink/modules/battery.py
lnxlink/modules/beacondb.py
lnxlink/modules/bluetooth.py
lnxlink/modules/boot_select.py
lnxlink/modules/brightness.py
lnxlink/modules/camera_used.py
lnxlink/modules/clipboard.py
lnxlink/modules/cpu.py
lnxlink/modules/disk_io.py
lnxlink/modules/disk_usage.py
lnxlink/modules/display_env.py
lnxlink/modules/docker.py
lnxlink/modules/fullscreen.py
lnxlink/modules/gamepad.py
lnxlink/modules/gpio.py
lnxlink/modules/gpu.py
lnxlink/modules/idle.py
lnxlink/modules/inference_time.py
lnxlink/modules/interfaces.py
lnxlink/modules/ir_remote.py
lnxlink/modules/keep_alive.py
lnxlink/modules/keyboard_hotkeys.py
lnxlink/modules/logging_level.py
lnxlink/modules/media.py
lnxlink/modules/memory.py
lnxlink/modules/microphone_used.py
lnxlink/modules/mounts.py
lnxlink/modules/mouse.py
lnxlink/modules/network.py
lnxlink/modules/notify.py
lnxlink/modules/power_profile.py
lnxlink/modules/required_restart.py
lnxlink/modules/restart.py
lnxlink/modules/restful.py
lnxlink/modules/screen_onoff.py
lnxlink/modules/screenshot.py
lnxlink/modules/send_keys.py
lnxlink/modules/shutdown.py
lnxlink/modules/speaker_used.py
lnxlink/modules/speech_recognition.py
lnxlink/modules/statistics.py
lnxlink/modules/steam.py
lnxlink/modules/suspend.py
lnxlink/modules/sys_updates.py
lnxlink/modules/systemd.py
lnxlink/modules/temperature.py
lnxlink/modules/update.py
lnxlink/modules/watch_changes.py
lnxlink/modules/webcam.py
lnxlink/modules/wifi.py
lnxlink/modules/wol.py
lnxlink/modules/xdg_open.py
lnxlink/modules/scripts/docker_update_status.py
lnxlink/modules/scripts/helpers.py
lnxlink/modules/scripts/monitor_brightness.py
lnxlink-2026.2.0.dist-info/LICENSE.md
lnxlink-2026.2.0.dist-info/METADATA
lnxlink-2026.2.0.dist-info/WHEEL
lnxlink-2026.2.0.dist-info/entry_points.txt
lnxlink-2026.2.0.dist-info/top_level.txt
lnxlink-2026.2.0.dist-info/RECORD
