Metadata-Version: 2.1
Name: lnxlink
Version: 2026.2.0
Summary: Internet Of Things (IOT) integration with Linux using MQTT
Home-page: https://bkbilly.github.io/lnxlink
Author-email: bkbilly <bkbilly@hotmail.com>
Project-URL: Source Code, https://github.com/bkbilly/lnxlink
Project-URL: Documentation, https://bkbilly.gitbook.io/lnxlink
Keywords: lnxlink
Classifier: Programming Language :: Python :: 3
Classifier: License :: OSI Approved :: MIT License
Classifier: Operating System :: Unix
Requires-Python: >=3.8.0
License-File: LICENSE.md
Requires-Dist: distro (>=1.9.0)
Requires-Dist: PyYAML (>=6.0.1)
Requires-Dist: paho-mqtt (>=2.1.0)
Requires-Dist: requests (>=2.31.0)
Requires-Dist: psutil (>=7.0.0)
Requires-Dist: inotify (>=0.2.10)
Requires-Dist: jeepney (>=0.9.0)
Requires-Dist: aiohttp (>=3.9.0)
Requires-Dist: asyncio (>=3.4.3)
Requires-Dist: beaupy (>=3.10.0)
